halstead_complexity/__init__.py
halstead_complexity/__main__.py
halstead_complexity/cli.py
halstead_complexity/config.py
halstead_complexity/default_config.json
halstead_complexity/metrics/analysis.py
halstead_complexity/metrics/halstead.py
halstead_complexity/metrics/raw_metrics.py
halstead_complexity/metrics/tree_utils.py
halstead_complexity-0.1.0.dist-info/METADATA
halstead_complexity-0.1.0.dist-info/WHEEL
halstead_complexity-0.1.0.dist-info/entry_points.txt
halstead_complexity-0.1.0.dist-info/licenses/LICENSE
halstead_complexity-0.1.0.dist-info/RECORD
