Metadata-Version: 2.4
Name: halstead-complexity
Version: 0.1.0
Summary: Measure Halstead code complexity
Project-URL: Source, https://github.com/EpicAlbin03/halstead-complexity
Author: EpicAlbin03
License-Expression: MIT
License-File: LICENSE
Keywords: analysis,code,complexity,halstead,metrics
Classifier: Development Status :: 3 - Alpha
Classifier: Environment :: Console
Classifier: Intended Audience :: Developers
Classifier: License :: OSI Approved :: MIT License
Classifier: Operating System :: OS Independent
Classifier: Programming Language :: Python :: 3
Classifier: Programming Language :: Python :: 3 :: Only
Classifier: Programming Language :: Python :: 3.12
Classifier: Topic :: Software Development
Classifier: Topic :: Software Development :: Quality Assurance
Classifier: Topic :: Software Development :: Testing
Classifier: Topic :: Utilities
Classifier: Typing :: Typed
Requires-Python: >=3.12
Requires-Dist: dynaconf>=3.2.11
Requires-Dist: platformdirs>=4.4.0
Requires-Dist: tree-sitter>=0.25.2
Requires-Dist: typer>=0.19.2
Provides-Extra: all
Requires-Dist: tree-sitter-javascript>=0.25.0; extra == 'all'
Requires-Dist: tree-sitter-python>=0.25.0; extra == 'all'
Provides-Extra: javascript
Requires-Dist: tree-sitter-javascript>=0.25.0; extra == 'javascript'
Provides-Extra: python
Requires-Dist: tree-sitter-python>=0.25.0; extra == 'python'
